{
  "description": "Rocking and Rolling at Head Crater",
  "transcript": [
    {
      "tokens": [
        "Lighting Annunciator/Numerics, Dim."
      ],
      "speaker": "Bean",
      "time": "131:35:36"
    },
    {
      "tokens": [
        "Okay, let me turn (to get the switch on the panel on the left side of the spacecraft)."
      ],
      "speaker": "Conrad",
      "time": "131:35:39"
    },
    {
      "tokens": [
        "Okay."
      ],
      "speaker": "Bean",
      "time": "131:35:40"
    },
    {
      "tokens": [
        "I'll have to come towards you (in order to get enough room behind him to get his PLSS around)."
      ],
      "speaker": "Conrad",
      "time": "131:35:42"
    },
    {
      "tokens": [
        "All right.",
        "(Pause)"
      ],
      "speaker": "Bean",
      "time": "131:35:43"
    },
    {
      "tokens": [
        "Dim."
      ],
      "speaker": "Conrad",
      "time": "131:35:52"
    },
    {
      "tokens": [
        "Okay.",
        "(Pause)"
      ],
      "speaker": "Bean",
      "time": "131:35:53"
    },
    {
      "tokens": [
        "I'm just...Easy.",
        "(Pause)"
      ],
      "speaker": "Conrad",
      "time": "131:35:59"
    },
    {
      "tokens": [
        "Tell you what; why don't you release my"
      ],
      "speaker": "Bean",
      "time": "131:36:05"
    },
    {
      "tokens": [
        "No, that flap right there.",
        "\"Flap.\" Okay."
      ],
      "speaker": "Conrad",
      "time": "131:36:08"
    },
    {
      "tokens": [
        "(Garbled) pulling mine and then when you go down (on hands and knees) to go out, I'll take yours up."
      ],
      "speaker": "Bean",
      "time": "131:36:15"
    },
    {
      "tokens": [
        "Okay.",
        "(Pause) Up."
      ],
      "speaker": "Conrad",
      "time": "131:36:17"
    },
    {
      "tokens": [
        "All right."
      ],
      "speaker": "Bean",
      "time": "131:36:23"
    },
    {
      "tokens": [
        "I'm ready to go."
      ],
      "speaker": "Conrad",
      "time": "131:36:25"
    },
    {
      "tokens": [
        "Okay.",
        "Just a second."
      ],
      "speaker": "Bean",
      "time": "131:36:29"
    },
    {
      "tokens": [
        "All right.",
        "Let me...Hold my knee against that...That Velcro doesn't hold worth a hoot.",
        "(Pause)"
      ],
      "speaker": "Conrad",
      "time": "131:36:30"
    },
    {
      "tokens": [
        "Okay; out you go."
      ],
      "speaker": "Bean",
      "time": "131:36:36"
    },
    {
      "tokens": [
        "Okay.",
        "(Pause) (Garbled) hung on there.",
        "See anything?"
      ],
      "speaker": "Conrad",
      "time": "131:36:38"
    },
    {
      "tokens": [
        "Nope."
      ],
      "speaker": "Bean",
      "time": "131:36:48"
    },
    {
      "tokens": [
        "Okay."
      ],
      "speaker": "Conrad",
      "time": "131:36:49"
    },
    {
      "tokens": [
        "That's the way; you're centered good this trip.",
        "(Pause) That's good.",
        "Move a little bit to the left.",
        "Little bit to the left.",
        "There you go.",
        "(Pause) Here, let me get that antenna as you go."
      ],
      "speaker": "Bean",
      "time": "131:36:52"
    },
    {
      "tokens": [
        "Okay."
      ],
      "speaker": "Conrad",
      "time": "131:37:04"
    },
    {
      "tokens": [
        "It's out."
      ],
      "speaker": "Bean",
      "time": "131:37:05"
    },
    {
      "tokens": [
        "Get it?"
      ],
      "speaker": "Conrad",
      "time": "131:37:06"
    },
    {
      "tokens": [
        "Yeah, ready to go."
      ],
      "speaker": "Bean",
      "time": "131:37:08"
    },
    {
      "tokens": [
        "Okay."
      ],
      "speaker": "Conrad",
      "time": "131:37:09"
    },
    {
      "tokens": [
        "Move a little bit to your right.",
        "(Pause) And you're out the hatch.",
        "And I'll be standing by to get the"
      ],
      "speaker": "Bean",
      "time": "131:37:10"
    },
    {
      "tokens": [
        "Wait a minute.",
        "(Garbled) going off; did the (jett) bag go off (the porch)?"
      ],
      "speaker": "Conrad",
      "time": "131:37:17"
    },
    {
      "tokens": [
        "I can't tell."
      ],
      "speaker": "Bean",
      "time": "131:37:22"
    },
    {
      "tokens": [
        "I can't either.",
        "(Pause) Okay.",
        "Good shape.",
        "Okay.",
        "You want to hand me the LEC?",
        "(Correcting himself) I mean the left-hand-side stowage; you want to get rid of it?",
        "Let's get rid of it."
      ],
      "speaker": "Conrad",
      "time": "131:37:24"
    },
    {
      "tokens": [
        "All right.",
        "(Pause) Okey-doke.",
        "Here it comes."
      ],
      "speaker": "Bean",
      "time": "131:37:45"
    },
    {
      "tokens": [
        "Okay.",
        "(Pause)"
      ],
      "speaker": "Conrad",
      "time": "131:37:50"
    },
    {
      "tokens": [
        "Just a second.",
        "(I'll) open the hatch a little more and give it a kick.",
        "(Pause) And I'm standing by for the LEC."
      ],
      "speaker": "Bean",
      "time": "131:37:56"
    },
    {
      "tokens": [
        "All right; wait a minute.",
        "(Pause) An LEC, coming at you.",
        "Ah, I've got to bring it up (farther, because Al can't reach out far enough to get the LEC from Pete's outstretched hand).",
        "Wait a minute."
      ],
      "speaker": "Conrad",
      "time": "131:38:13"
    },
    {
      "tokens": [
        "Okay.",
        "(Pause) Got it."
      ],
      "speaker": "Bean",
      "time": "131:38:21"
    },
    {
      "tokens": [
        "There you go.",
        "I'm headed down the ladder."
      ],
      "speaker": "Conrad",
      "time": "131:38:26"
    },
    {
      "tokens": [
        "All right."
      ],
      "speaker": "Bean",
      "time": "131:38:28"
    },
    {
      "tokens": [
        "Down to campus (for their final geology exam)."
      ],
      "speaker": "Conrad",
      "time": "131:38:29"
    },
    {
      "tokens": [
        "Okay.",
        "(Long Pause)"
      ],
      "speaker": "Bean",
      "time": "131:38:32"
    },
    {
      "tokens": [
        "Whoops, long step.",
        "(Pause) Okay, Houston, Mark.",
        "I'm on the lunar surface."
      ],
      "speaker": "Conrad",
      "time": "131:38:50"
    },
    {
      "tokens": [
        "Roger.",
        "Copy, Pete."
      ],
      "speaker": "Gibson",
      "time": "131:39:01"
    },
    {
      "tokens": [
        "One of these contrast charts fell down here yesterday, Al.",
        "So there's only two good ones; the other one's too dirty."
      ],
      "speaker": "Conrad",
      "time": "131:40:25"
    },
    {
      "tokens": [
        "All right."
      ],
      "speaker": "Bean",
      "time": "131:40:31"
    },
    {
      "tokens": [
        "It (the dust clinging to the chart) doesn't rap off; it just...(Pause)"
      ],
      "speaker": "Conrad",
      "time": "131:40:32"
    },
    {
      "tokens": [
        "Okay, ready to transfer ETB when you are."
      ],
      "speaker": "Bean",
      "time": "131:40:41"
    },
    {
      "tokens": [
        "Okay.",
        "(Pause) Coming right after it, right now."
      ],
      "speaker": "Conrad",
      "time": "131:40:43"
    },
    {
      "tokens": [
        "Looks like the lock on the LEC is kind of jammed with..."
      ],
      "speaker": "Bean",
      "time": "131:40:52"
    },
    {
      "tokens": [
        "Dirt?"
      ],
      "speaker": "Conrad",
      "time": "131:41:03"
    },
    {
      "tokens": [
        "Dirt, yeah.",
        "(Long Pause)"
      ],
      "speaker": "Bean",
      "time": "131:41:04"
    },
    {
      "tokens": [
        "Pull away."
      ],
      "speaker": "Bean",
      "time": "131:41:21"
    },
    {
      "tokens": [
        "Huh?"
      ],
      "speaker": "Conrad",
      "time": "131:41:23"
    },
    {
      "tokens": [
        "Pull away!"
      ],
      "speaker": "Bean",
      "time": "131:41:24"
    },
    {
      "tokens": [
        "(You're) pulling me.",
        "You have to let it out easier.",
        "Okay; let it go.",
        "Just lower it.",
        "Lower.",
        "All right, just lower it some more.",
        "All right, hold it right there."
      ],
      "speaker": "Conrad",
      "time": "131:41:26"
    },
    {
      "tokens": [
        "Okay."
      ],
      "speaker": "Bean",
      "time": "131:41:40"
    },
    {
      "tokens": [
        "Boy, I'll tell you, two things I'm going to learn to dislike: and one of them's the TV cable and the other one's the S-band antenna cable."
      ],
      "speaker": "Conrad",
      "time": "131:41:43"
    },
    {
      "tokens": [
        "Roger, Pete.",
        "We copy that."
      ],
      "speaker": "Gibson",
      "time": "131:41:52"
    },
    {
      "tokens": [
        "And they are constantly underfoot.",
        "(See AS12-46-"
      ],
      "speaker": "Conrad",
      "time": "131:41:58"
    },
    {
      "tokens": [
        "Okay."
      ],
      "speaker": "Bean",
      "time": "131:42:17"
    },
    {
      "tokens": [
        "Al, before egress, would you confirm that the TV circuit breaker is out?"
      ],
      "speaker": "Gibson",
      "time": "131:42:21"
    },
    {
      "tokens": [
        "Confirmed; out."
      ],
      "speaker": "Bean",
      "time": "131:42:28"
    },
    {
      "tokens": [
        "Roger."
      ],
      "speaker": "Gibson",
      "time": "131:42:30"
    },
    {
      "tokens": [
        "It is out, Houston."
      ],
      "speaker": "Bean",
      "time": "131:42:32"
    },
    {
      "tokens": [
        "Roger, Al."
      ],
      "speaker": "Gibson",
      "time": "131:42:35"
    },
    {
      "tokens": [
        "Okay.",
        "(Pause)"
      ],
      "speaker": "Bean",
      "time": "131:42:38"
    },
    {
      "tokens": [
        "Oh, my friendly gnomon.",
        "In all the (garbled) activity yesterday, I forgot all about him sitting here."
      ],
      "speaker": "Conrad",
      "time": "131:42:48"
    },
    {
      "tokens": [
        "What you up to, Al?"
      ],
      "speaker": "Conrad",
      "time": "131:44:21"
    },
    {
      "tokens": [
        "Getting this (16 mm sequence) camera set."
      ],
      "speaker": "Bean",
      "time": "131:44:23"
    },
    {
      "tokens": [
        "Okay.",
        "Got SRC 2.",
        "(Pause) Working away here.",
        "(Long Pause)"
      ],
      "speaker": "Conrad",
      "time": "131:44:24"
    },
    {
      "tokens": [
        "Okay.",
        "Let me"
      ],
      "speaker": "Bean",
      "time": "131:44:55"
    },
    {
      "tokens": [
        "Okay.",
        "(Long Pause)"
      ],
      "speaker": "Conrad",
      "time": "131:44:59"
    },
    {
      "tokens": [
        "Okay on that side.",
        "(Pause) And 11 (Pete's CB panel) now.",
        "(Long Pause)"
      ],
      "speaker": "Bean",
      "time": "131:45:13"
    },
    {
      "tokens": [
        "I'll tell you, these Teflon bags don't hold up too well in a vacuum.",
        "\"In a lunar environment;\" I'll put it that way."
      ],
      "speaker": "Conrad",
      "time": "131:45:44"
    },
    {
      "tokens": [
        "Roger, Pete.",
        "We copy that comment.",
        "Any clarification?"
      ],
      "speaker": "Gibson",
      "time": "131:45:54"
    },
    {
      "tokens": [
        "Yeah, they tend to have fatigue failures along the cracks (that is, along the side folds) when you go to open them up.",
        "I notice the two bags that I put in the SRC yesterday were that way.",
        "And, let me get back here (into the sunlight) just a second.",
        "Let's see.",
        "(Reading) \"Pass LEC; ETB transfer; geology Prep; stow on HTC: contrast charts, extension handle, hammer, small shovel, and gnomon.\""
      ],
      "speaker": "Conrad",
      "time": "131:46:00"
    },
    {
      "tokens": [
        "Here I come.",
        "Pete."
      ],
      "speaker": "Bean",
      "time": "131:46:22"
    },
    {
      "tokens": [
        "Okay, have fun.",
        "(Reading) \"Place SRC 2 on MESA; attach weigh bag to scale; attach saddlebag to LMP.\" There's one thing that's bothering me; I don't have that saddlebag.",
        "I wonder why I don't?",
        "Where might I find one?",
        "(Pause) Ah, ha, ha!",
        "Here's one.",
        "(To Al) How are you doing?"
      ],
      "speaker": "Conrad",
      "time": "131:46:23"
    },
    {
      "tokens": [
        "Good."
      ],
      "speaker": "Bean",
      "time": "131:46:51"
    },
    {
      "tokens": [
        "(Offering to watch Al come out through the hatch) Let me check.",
        "Okay.",
        "Keep coming.",
        "Super good shape.",
        "There you go.",
        "A little left.",
        "(Garbled under Al)"
      ],
      "speaker": "Conrad",
      "time": "131:46:53"
    },
    {
      "tokens": [
        "Wait a minute while I try to close this hatch."
      ],
      "speaker": "Bean",
      "time": "131:47:01"
    },
    {
      "tokens": [
        "Oh, okay.",
        "(Long Pause)"
      ],
      "speaker": "Conrad",
      "time": "131:47:03"
    },
    {
      "tokens": [
        "Right now, this stuff...(correcting himself) this \"material\" around the spacecraft reminds me...In this Sun angle, looking into the Sun, (it's) a very rich brown color, (and it) kind of reminds me of a good plowed field."
      ],
      "speaker": "Conrad",
      "time": "131:47:34"
    },
    {
      "tokens": [
        "Roger, Pete."
      ],
      "speaker": "Gibson",
      "time": "131:47:59"
    },
    {
      "tokens": [
        "Looking down-Sun, it's still the same old ash gray; very light, white, ash gray.",
        "(Long Pause)"
      ],
      "speaker": "Conrad",
      "time": "131:48:00"
    },
    {
      "tokens": [
        "Okay.",
        "LMP's off the footpad."
      ],
      "speaker": "Bean",
      "time": "131:48:40"
    },
    {
      "tokens": [
        "Okay, LMP.",
        "How about let's get a Surveyor parts bag here?"
      ],
      "speaker": "Conrad",
      "time": "131:48:44"
    },
    {
      "tokens": [
        "All right.",
        "Just a second, Pete."
      ],
      "speaker": "Bean",
      "time": "131:48:54"
    },
    {
      "tokens": [
        "All right."
      ],
      "speaker": "Conrad",
      "time": "131:48:55"
    },
    {
      "tokens": [
        "Pull down my blinders."
      ],
      "speaker": "Bean",
      "time": "131:48:56"
    },
    {
      "tokens": [
        "Huh?"
      ],
      "speaker": "Conrad",
      "time": "131:48:57"
    },
    {
      "tokens": [
        "I'm going to pull down those little side visors."
      ],
      "speaker": "Bean",
      "time": "131:48:58"
    },
    {
      "tokens": [
        "Houston.",
        "I think Al and I both find that these little side Sun visors are extremely handy."
      ],
      "speaker": "Conrad",
      "time": "131:49:02"
    },
    {
      "tokens": [
        "Roger, Pete.",
        "We copy."
      ],
      "speaker": "Gibson",
      "time": "131:49:13"
    },
    {
      "tokens": [
        "(Garbled) this strap down (on the Surveyor parts bag).",
        "(Long Pause)"
      ],
      "speaker": "Conrad",
      "time": "131:49:14"
    },
    {
      "tokens": [
        "Almost cold today (in the LM shadow) on mid-cooling.",
        "How are you doing?"
      ],
      "speaker": "Conrad",
      "time": "131:49:41"
    },
    {
      "tokens": [
        "About the same.",
        "(Garbled) that line right there, Pete."
      ],
      "speaker": "Bean",
      "time": "131:49:44"
    },
    {
      "tokens": [
        "Say again."
      ],
      "speaker": "Conrad",
      "time": "131:49:50"
    },
    {
      "tokens": [
        "I'm going to set the tether (safety line) right there and..."
      ],
      "speaker": "Bean",
      "time": "131:49:51"
    },
    {
      "tokens": [
        "Okay.",
        "(Pause)"
      ],
      "speaker": "Conrad",
      "time": "131:49:54"
    },
    {
      "tokens": [
        "Okay; and I'll put it (the Surveyor parts bag) on you here, babe."
      ],
      "speaker": "Bean",
      "time": "131:50:00"
    },
    {
      "tokens": [
        "How's that?",
        "(Do) you want me to stand low or high?"
      ],
      "speaker": "Conrad",
      "time": "131:50:05"
    },
    {
      "tokens": [
        "Low."
      ],
      "speaker": "Bean",
      "time": "131:50:08"
    },
    {
      "tokens": [
        "Okay.",
        "How's that?"
      ],
      "speaker": "Conrad",
      "time": "131:50:09"
    },
    {
      "tokens": [
        "Good.",
        "Okay, got that one on - (garbled) the side.",
        "Looking good so far.",
        "(Pause)"
      ],
      "speaker": "Bean",
      "time": "131:50:12"
    },
    {
      "tokens": [
        "You know, other than the large-size rocks, (it's) very, very difficult to determine a contact around here.",
        "(Pause)"
      ],
      "speaker": "Conrad",
      "time": "131:50:30"
    },
    {
      "tokens": [
        "Okay; (garbled).",
        "(Pause) Okay.",
        "Go around to the side.",
        "We're putting the parts bag on Pete right now, Houston."
      ],
      "speaker": "Bean",
      "time": "131:50:40"
    },
    {
      "tokens": [
        "(Garbled, possibly \"Hold on.\")"
      ],
      "speaker": "Conrad",
      "time": "131:50:57"
    },
    {
      "tokens": [
        "Okay.",
        "I will."
      ],
      "speaker": "Bean",
      "time": "131:50:58"
    },
    {
      "tokens": [
        "Roger.",
        "We copy that."
      ],
      "speaker": "Gibson",
      "time": "131:51:00"
    },
    {
      "tokens": [
        "Boy, Houston.",
        "That Comm is super; it sounds like you're right inside my helmet."
      ],
      "speaker": "Conrad",
      "time": "131:51:05"
    },
    {
      "tokens": [
        "Roger.",
        "It's the best sim(ulated EVA) we've had."
      ],
      "speaker": "Gibson",
      "time": "131:51:09"
    },
    {
      "tokens": [
        "I wonder what happened since yesterday?"
      ],
      "speaker": "Bean",
      "time": "131:51:16"
    },
    {
      "tokens": [
        "I don't know.",
        "I think everybody learns a little bit..."
      ],
      "speaker": "Conrad",
      "time": "131:51:22"
    },
    {
      "tokens": [
        "Okay."
      ],
      "speaker": "Bean",
      "time": "131:51:24"
    },
    {
      "tokens": [
        "...each time."
      ],
      "speaker": "Conrad",
      "time": "131:51:25"
    },
    {
      "tokens": [
        "That bag's on there; now, let's see what else (is on the checklist)."
      ],
      "speaker": "Bean",
      "time": "131:51:26"
    },
    {
      "tokens": [
        "I need to get the (bolt-cutting) tool.",
        "Hold the phone.",
        "(Pause) And before you put the tool in (the Surveyor parts bag), we got to cut a TV cable."
      ],
      "speaker": "Conrad",
      "time": "131:51:28"
    },
    {
      "tokens": [
        "That's affirmative.",
        "Cut the TV cable below the adapter, about 1 inch and then...(correcting himself) that's 1 foot below the adapter, and then stow the TV camera in the ETB."
      ],
      "speaker": "Gibson",
      "time": "131:51:38"
    },
    {
      "tokens": [
        "Okay.",
        "(Long Pause) Hey, look at that Surveyor, Al.",
        "That's not anywheres near as bad a slope (as it had seemed during EVA-1)."
      ],
      "speaker": "Conrad",
      "time": "131:51:50"
    },
    {
      "tokens": [
        "LM Crew: (Garbled) shade."
      ],
      "speaker": "Unknown",
      "time": "131:52:09"
    },
    {
      "tokens": [
        "Hey, Houston, that Surveyor looks a lot better today."
      ],
      "speaker": "Bean",
      "time": "131:52:11"
    },
    {
      "tokens": [
        "Yeah, now that the Sun's up on it."
      ],
      "speaker": "Conrad",
      "time": "131:52:13"
    },
    {
      "tokens": [
        "Get some Sun on it.",
        "(Garbled) yesterday."
      ],
      "speaker": "Bean",
      "time": "131:52:14"
    },
    {
      "tokens": [
        "Get those TV cables cut.",
        "Al, wait a minute; leave it (the TV camera) right on there (on the tripod) for a second.",
        "Come on over and put the thing (the bolt cutter) in my back (that is, in the parts bag) and let's mount our (Hasselblad) cameras and then the ETB is empty (to receive the TV camera)."
      ],
      "speaker": "Conrad",
      "time": "131:52:16"
    },
    {
      "tokens": [
        "All right.",
        "Sounds good."
      ],
      "speaker": "Bean",
      "time": "131:52:26"
    },
    {
      "tokens": [
        "Or either that, (or) bring it (the TV camera) back...I'm sorry."
      ],
      "speaker": "Conrad",
      "time": "131:52:27"
    },
    {
      "tokens": [
        "It's okay.",
        "Doesn't make any difference.",
        "(Garbled) (Pause)"
      ],
      "speaker": "Bean",
      "time": "131:52:28"
    },
    {
      "tokens": [
        "I think you got the right..."
      ],
      "speaker": "Conrad",
      "time": "131:52:37"
    },
    {
      "tokens": [
        "Here."
      ],
      "speaker": "Bean",
      "time": "131:52:38"
    },
    {
      "tokens": [
        "...got the right idea.",
        "That's the lunar walk."
      ],
      "speaker": "Conrad",
      "time": "131:52:39"
    },
    {
      "tokens": [
        "Okay.",
        "Stick it in here."
      ],
      "speaker": "Bean",
      "time": "131:52:45"
    },
    {
      "tokens": [
        "Look at that part number on the side of the tool.",
        "(Pause)"
      ],
      "speaker": "Conrad",
      "time": "131:52:47"
    },
    {
      "tokens": [
        "(Chuckling) Use that a few times."
      ],
      "speaker": "Bean",
      "time": "131:52:57"
    },
    {
      "tokens": [
        "Say, Houston, while he's putting the tool on, it's a very interesting thing.",
        "There is a angular rock that's literally 6 inches from the engine exhaust skirt.",
        "It's just sitting on the lunar surface; and I really find it hard to believe that the engine exhaust couldn't blow that rock away.",
        "It's only about 3-1/2 inches by 3-1/2 inches; and it's not stuck in the ground; it's just sitting there loosely about 6 inches from the engine bell; and, of course, the ground is blasted clean all the way around it and yet the engine exhaust blast didn't blow that rock away."
      ],
      "speaker": "Conrad",
      "time": "131:53:01"
    },
    {
      "tokens": [
        "Pete, where's the saddlebag?"
      ],
      "speaker": "Bean",
      "time": "131:53:37"
    },
    {
      "tokens": [
        "Roger, Pete.",
        "We copied that comment.",
        "Were you able to get a photo of that in the first EVA?"
      ],
      "speaker": "Gibson",
      "time": "131:53:40"
    },
    {
      "tokens": [
        "No, we'll get that right now.",
        "Is there one (that is, a saddlebag) in here, Al?"
      ],
      "speaker": "Conrad",
      "time": "131:53:47"
    },
    {
      "tokens": [
        "Yeah."
      ],
      "speaker": "Bean",
      "time": "131:53:52"
    },
    {
      "tokens": [
        "Oh.",
        "(Pause)"
      ],
      "speaker": "Conrad",
      "time": "131:53:53"
    },
    {
      "tokens": [
        "And, Pete and Al, for your reference on the photos, your shadow length now is 18 foot."
      ],
      "speaker": "Gibson",
      "time": "131:54:01"
    },
    {
      "tokens": [
        "Okay.",
        "(To Pete) Here's a couple of sneaky bags (that is, saddlebags) for us."
      ],
      "speaker": "Bean",
      "time": "131:54:08"
    },
    {
      "tokens": [
        "Al, also if you would, before you start that traverse, would you get a good photo of the solar wind to show us how that foil is wrapped around?"
      ],
      "speaker": "Gibson",
      "time": "131:54:14"
    },
    {
      "tokens": [
        "Will do.",
        "Okay, Houston, that won't take a second.",
        "Okay, let me attach this bag to...Would you attach this bag to me, Pete?"
      ],
      "speaker": "Bean",
      "time": "131:54:26"
    },
    {
      "tokens": [
        "Yeah.",
        "(Pause)"
      ],
      "speaker": "Conrad",
      "time": "131:54:34"
    },
    {
      "tokens": [
        "I'm going to slide that off at the same time."
      ],
      "speaker": "Bean",
      "time": "131:54:39"
    },
    {
      "tokens": [
        "All right.",
        "(Pause) Okay, I'll tell you what, if you go put one camera...Here, the saddlebag's on...if you'd put one (70mm Hasselblad) camera on..."
      ],
      "speaker": "Conrad",
      "time": "131:54:42"
    },
    {
      "tokens": [
        "Look at those little..."
      ],
      "speaker": "Bean",
      "time": "131:55:00"
    },
    {
      "tokens": [
        "...Go get the TV, I'll mount this other gear on here (that is, on the HTC).",
        "My compliments to the man that packed that SRC box; it looks just like the training boxes."
      ],
      "speaker": "Conrad",
      "time": "131:55:01"
    },
    {
      "tokens": [
        "Hand me those tongs a second."
      ],
      "speaker": "Bean",
      "time": "131:55:16"
    },
    {
      "tokens": [
        "Yes, sir.",
        "Here's the tongs.",
        "(Pause) Where are you?"
      ],
      "speaker": "Conrad",
      "time": "131:55:17"
    },
    {
      "tokens": [
        "Right behind you.",
        "Wait; hold on just a second.",
        "Hold on; let's see what this is."
      ],
      "speaker": "Bean",
      "time": "131:55:23"
    },
    {
      "tokens": [
        "That's what left of..."
      ],
      "speaker": "Conrad",
      "time": "131:55:31"
    },
    {
      "tokens": [
        "Okay, got you."
      ],
      "speaker": "Bean",
      "time": "131:55:33"
    },
    {
      "tokens": [
        "...one of those parts bags (he may mean the remnants of a weigh bag)."
      ],
      "speaker": "Conrad",
      "time": "131:55:34"
    },
    {
      "tokens": [
        "Got you.",
        "Okay.",
        "(Pause)"
      ],
      "speaker": "Bean",
      "time": "131:55:35"
    },
    {
      "tokens": [
        "Okay; core tubes.",
        "(Pause) (Talking to the core tube) Come on; get out of there.",
        "If I didn't know better, I'd say there was solar wind up here (pause) that blows hard enough to blow sample bags in the wrong direction.",
        "(Pause) Okay, Al, three core tubes in the deal (that is, in the HTC)."
      ],
      "speaker": "Conrad",
      "time": "131:55:46"
    },
    {
      "tokens": [
        "Okay; (garbled)."
      ],
      "speaker": "Bean",
      "time": "131:56:24"
    },
    {
      "tokens": [
        "Dixie cup dispenser coming up.",
        "(Pause)"
      ],
      "speaker": "Conrad",
      "time": "131:56:31"
    },
    {
      "tokens": [
        "Could you (garbled)?",
        "(Long Pause)"
      ],
      "speaker": "Bean",
      "time": "131:56:43"
    },
    {
      "tokens": [
        "Saddlebag.",
        "(Pause) Chart fits right in its spot.",
        "Worried about that.",
        "Got it?"
      ],
      "speaker": "Bean",
      "time": "131:57:05"
    },
    {
      "tokens": [
        "Yes, sir.",
        "It's in the saddlebag."
      ],
      "speaker": "Conrad",
      "time": "131:57:18"
    },
    {
      "tokens": [
        "Okay."
      ],
      "speaker": "Bean",
      "time": "131:57:19"
    },
    {
      "tokens": [
        "Now here's the other thing here."
      ],
      "speaker": "Conrad",
      "time": "131:57:21"
    },
    {
      "tokens": [
        "That safety line."
      ],
      "speaker": "Bean",
      "time": "131:57:22"
    },
    {
      "tokens": [
        "Huh?",
        "Oh, yeah.",
        "(Pause) Why don't I hook those on there, too.",
        "That thing (probably the pack of flat sample bags)'s a pain in the neck over there, the way they spread out in the vacuum."
      ],
      "speaker": "Conrad",
      "time": "131:57:24"
    },
    {
      "tokens": [
        "Okay."
      ],
      "speaker": "Bean",
      "time": "131:57:33"
    },
    {
      "tokens": [
        "And I got the gas sample tube here."
      ],
      "speaker": "Conrad",
      "time": "131:57:34"
    },
    {
      "tokens": [
        "All right."
      ],
      "speaker": "Bean",
      "time": "131:57:35"
    },
    {
      "tokens": [
        "Gas sample tube coming up."
      ],
      "speaker": "Conrad",
      "time": "131:57:39"
    },
    {
      "tokens": [
        "Okay.",
        "Now I need to get that safety line.",
        "Okay; I'll put that over here."
      ],
      "speaker": "Bean",
      "time": "131:57:43"
    },
    {
      "tokens": [
        "Okay, I'll get the safety line.",
        "One safety line...Whoops, excuse me."
      ],
      "speaker": "Conrad",
      "time": "131:57:49"
    },
    {
      "tokens": [
        "That's okay."
      ],
      "speaker": "Bean",
      "time": "131:57:53"
    },
    {
      "tokens": [
        "I'll put my (70mm) camera on; we'll put the TV camera in the ETB; and away we go."
      ],
      "speaker": "Conrad",
      "time": "131:57:55"
    },
    {
      "tokens": [
        "Okay; we need to take..."
      ],
      "speaker": "Bean",
      "time": "131:58:01"
    },
    {
      "tokens": [
        "Here."
      ],
      "speaker": "Conrad",
      "time": "131:58:02"
    },
    {
      "tokens": [
        "All right."
      ],
      "speaker": "Bean",
      "time": "131:58:03"
    },
    {
      "tokens": [
        "Wait a...Right there.",
        "(Pause)"
      ],
      "speaker": "Conrad",
      "time": "131:58:04"
    },
    {
      "tokens": [
        "Got it?"
      ],
      "speaker": "Bean",
      "time": "131:58:10"
    },
    {
      "tokens": [
        "Yes, sir.",
        "It's in."
      ],
      "speaker": "Conrad",
      "time": "131:58:11"
    },
    {
      "tokens": [
        "Okay.",
        "If you get your (70mm) camera, I'll put that TV camera in the ETB."
      ],
      "speaker": "Bean",
      "time": "131:58:12"
    },
    {
      "tokens": [
        "Okay."
      ],
      "speaker": "Conrad",
      "time": "131:58:16"
    },
    {
      "tokens": [
        "Per their request.",
        "(Pause)"
      ],
      "speaker": "Bean",
      "time": "131:58:17"
    },
    {
      "tokens": [
        "Okay, from the local terrain, Houston, as you know it right now, and with the polarizing filter, have you got any particular place enroute to the ALSEP or to Head Crater that you'd like any polarizing pictures taken?"
      ],
      "speaker": "Conrad",
      "time": "131:58:24"
    },
    {
      "tokens": [
        "Okay, from the local terrain, Houston, as you know it right now, and with the polarizing filter, have you got any particular place enroute to the ALSEP or to Head Crater that you'd like any polarizing pictures taken?"
      ],
      "speaker": "Conrad",
      "time": "131:58:24"
    },
    {
      "tokens": [
        "We'll get back to you on that.",
        "Press on now with the nominal plan right now."
      ],
      "speaker": "Gibson",
      "time": "131:58:43"
    },
    {
      "tokens": [
        "(To Al) Here, let me have it (the TV camera)."
      ],
      "speaker": "Conrad",
      "time": "131:58:51"
    },
    {
      "tokens": [
        "Okay, let me fold the handle."
      ],
      "speaker": "Bean",
      "time": "131:58:53"
    },
    {
      "tokens": [
        "Fold the handle, yeah.",
        "(Pause)"
      ],
      "speaker": "Conrad",
      "time": "131:58:54"
    },
    {
      "tokens": [
        "Hold it tight."
      ],
      "speaker": "Bean",
      "time": "131:58:58"
    },
    {
      "tokens": [
        "I got it as far as I can.",
        "(Pause)"
      ],
      "speaker": "Conrad",
      "time": "131:58:59"
    },
    {
      "tokens": [
        "Pete, we have no preference on that.",
        "(That is, Houston has no preference with regard to a location for the pictures to be taken with the polarizing filter.) Go ahead and take it as called out for in the cuff checklist."
      ],
      "speaker": "Gibson",
      "time": "131:59:06"
    },
    {
      "tokens": [
        "(To Al) Okay.",
        "Stick it in the ETB and we'll screw with it (meaning the TV) later."
      ],
      "speaker": "Conrad",
      "time": "131:59:14"
    },
    {
      "tokens": [
        "Good idea."
      ],
      "speaker": "Bean",
      "time": "131:59:16"
    },
    {
      "tokens": [
        "Handle in."
      ],
      "speaker": "Conrad",
      "time": "131:59:17"
    },
    {
      "tokens": [
        "Okay."
      ],
      "speaker": "Bean",
      "time": "131:59:18"
    },
    {
      "tokens": [
        "(Don't) drop her.",
        "Okay, Houston, one TV camera in the bag.",
        "And our plan of attack is...Al?"
      ],
      "speaker": "Conrad",
      "time": "131:59:19"
    },
    {
      "tokens": [
        "Go."
      ],
      "speaker": "Bean",
      "time": "131:59:31"
    },
    {
      "tokens": [
        "(Get) one picture of that rock under the descent stage;..."
      ],
      "speaker": "Conrad",
      "time": "131:59:33"
    },
    {
      "tokens": [
        "Will do."
      ],
      "speaker": "Bean",
      "time": "131:59:36"
    },
    {
      "tokens": [
        "...(then) grab the Hand Tool Carrier and head for the solar wind and grab a picture of that.",
        "In the meantime, I'll lope off to the ALSEP and check the SIDE.",
        "I'll meet you at Point 1 at Head Crater."
      ],
      "speaker": "Conrad",
      "time": "131:59:37"
    },
    {
      "tokens": [
        "Roger; we copy."
      ],
      "speaker": "Gibson",
      "time": "131:59:49"
    },
    {
      "tokens": [
        "And, Al, have you gotten the readings on the contrast charts?"
      ],
      "speaker": "Gibson",
      "time": "131:59:51"
    },
    {
      "tokens": [
        "Not yet; and I plan to do that real quick."
      ],
      "speaker": "Bean",
      "time": "131:59:57"
    },
    {
      "tokens": [
        "Roger."
      ],
      "speaker": "Gibson",
      "time": "132:00:00"
    },
    {
      "tokens": [
        "Houston, Pete's on his way to the ALSEP."
      ],
      "speaker": "Conrad",
      "time": "132:00:01"
    },
    {
      "tokens": [
        "(Making a mis-identification) Roger, Al; we copy.",
        "And at 30 minutes into the EVA, you're pretty close to the nominal time line."
      ],
      "speaker": "Gibson",
      "time": "132:00:08"
    },
    {
      "tokens": [
        "Okay."
      ],
      "speaker": "Bean",
      "time": "132:00:17"
    },
    {
      "tokens": [
        "Very good.",
        "(Pause) Can the guy with the seismometer hear me running?"
      ],
      "speaker": "Conrad",
      "time": "132:00:18"
    },
    {
      "tokens": [
        "(Garbled; possibly something about a camera setting) (Long Pause) Okay."
      ],
      "speaker": "Bean",
      "time": "132:00:36"
    },
    {
      "tokens": [
        "Pete, we're watching you down here on the seismic data.",
        "Looks as though you're really thundering right by it."
      ],
      "speaker": "Gibson",
      "time": "132:01:11"
    },
    {
      "tokens": [
        "Yeah, I ground to a halt there to"
      ],
      "speaker": "Conrad",
      "time": "132:01:20"
    },
    {
      "tokens": [
        "Roger.",
        "And we were able to copy (that is, sense) your rest and now that you're moving again (on the seismometer)."
      ],
      "speaker": "Gibson",
      "time": "132:01:41"
    },
    {
      "tokens": [
        "Okay.",
        "(Pause) All right, Houston.",
        "The (CCIG) status is...Oops, I'm going to get dust in it.",
        "The cover is off, and it's pointed up at the sky at about a 60-degree angle."
      ],
      "speaker": "Conrad",
      "time": "132:01:48"
    },
    {
      "tokens": [
        "Roger.",
        "Do not touch it right now, Pete.",
        "Which way is that pointing, relative to east-west?"
      ],
      "speaker": "Gibson",
      "time": "132:02:09"
    },
    {
      "tokens": [
        "It is pointed down-Sun (that is, west)."
      ],
      "speaker": "Conrad",
      "time": "132:02:19"
    },
    {
      "tokens": [
        "Roger.",
        "(Pause) Pete, no need to change the configuration; let's press on.",
        "(Pause) We copy that you've stopped on the seismic."
      ],
      "speaker": "Gibson",
      "time": "132:02:23"
    },
    {
      "tokens": [
        "Yeah.",
        "Where's me handy-dandy LMP?"
      ],
      "speaker": "Conrad",
      "time": "132:02:41"
    },
    {
      "tokens": [
        "He's contrast charting."
      ],
      "speaker": "Bean",
      "time": "132:02:47"
    },
    {
      "tokens": [
        "Oh, okay.",
        "Meet you at the Head Crater, pal."
      ],
      "speaker": "Conrad",
      "time": "132:02:49"
    },
    {
      "tokens": [
        "Okay.",
        "(Pause)"
      ],
      "speaker": "Bean",
      "time": "132:02:52"
    },
    {
      "tokens": [
        "Oh, boy, is that...I want that rock.",
        "That is a dandy extra grapefruit-size-type goody.",
        "(Pause)"
      ],
      "speaker": "Conrad",
      "time": "132:02:57"
    },
    {
      "tokens": [
        "(I need to) find a crater with a shadow in it first.",
        "There's one.",
        "(Pause) Okay, Houston, I'm approaching a crater now and I'm going to put the contrast chart in it.",
        "One (photo taken with the chart placed) on each side (of the contact between sunlight and shadow).",
        "One on the sunny side, one on the shadow side.",
        "(Garbled)"
      ],
      "speaker": "Bean",
      "time": "132:03:07"
    },
    {
      "tokens": [
        "Roger.",
        "(Pause)"
      ],
      "speaker": "Gibson",
      "time": "132:03:35"
    },
    {
      "tokens": [
        "Okay.",
        "There's the one on the sunny side."
      ],
      "speaker": "Bean",
      "time": "132:03:44"
    },
    {
      "tokens": [
        "Man, have I got the grapefruit rock of all grapefruit rocks!",
        "That's got to come home in the spacecraft; it'll never fit in the rock box.",
        "(Pause) Okay, Houston, I'll tell you what I'm going to do.",
        "I'm going to wind up at the right place at Head Crater; and, while I'm waiting for Al, I'll roll a boulder for you."
      ],
      "speaker": "Conrad",
      "time": "132:03:46"
    },
    {
      "tokens": [
        "Sounds good, Pete."
      ],
      "speaker": "Schmitt",
      "time": "132:04:07"
    },
    {
      "tokens": [
        "I'm now looking at the contrast...(Pause) (Sub vocal, taking a picture of the contrast chart on a level surface) Five (feet focus) and one (picture)."
      ],
      "speaker": "Bean",
      "time": "132:04:09"
    },
    {
      "tokens": [
        "Pete, Houston.",
        "Can you give us a mark when you roll?",
        "Over"
      ],
      "speaker": "Schmitt",
      "time": "132:04:14"
    },
    {
      "tokens": [
        "That crater is...(Answering Houston) Yeah, I sure will.",
        "Head Crater is, by golly, a rather steep crater; a lot steeper than it looks from out the LM.",
        "It's..."
      ],
      "speaker": "Conrad",
      "time": "132:04:20"
    },
    {
      "tokens": [
        "Houston?"
      ],
      "speaker": "Bean",
      "time": "132:04:37"
    },
    {
      "tokens": [
        "Yeah, go."
      ],
      "speaker": "Schmitt",
      "time": "132:04:39"
    },
    {
      "tokens": [
        "I'm looking at the contrast chart in the Sun and I can see all the different shades.",
        "Okay, now I've taken a photo of it; now I'll look at the one in the shadow.",
        "In the shadow, I can see...Well, it kind of depends on how close I am.",
        "If I'm within about 3 feet of it or 4 feet of it, I can see all six shades.",
        "I'll take a picture here, then I'll back up."
      ],
      "speaker": "Bean",
      "time": "132:04:43"
    },
    {
      "tokens": [
        "Let me ask you a question, Houston.",
        "How big a rock?"
      ],
      "speaker": "Conrad",
      "time": "132:05:10"
    },
    {
      "tokens": [
        "Pete, Houston.",
        "I presume whatever's a convenient size for you.",
        "We'll check that out though."
      ],
      "speaker": "Schmitt",
      "time": "132:05:17"
    },
    {
      "tokens": [
        "(chuckles) How about a grapefruit-size rock?",
        "That's what I'm holding in my hand and these other rocks that I was talking to you about are pretty well buried, and they're pretty large.",
        "I don't think I could get one of them going."
      ],
      "speaker": "Conrad",
      "time": "132:05:27"
    },
    {
      "tokens": [
        "Houston?"
      ],
      "speaker": "Bean",
      "time": "132:05:39"
    },
    {
      "tokens": [
        "(To Pete) Roger.",
        "We copy.",
        "Grapefruit-size or any size is fine."
      ],
      "speaker": "Schmitt",
      "time": "132:05:40"
    },
    {
      "tokens": [
        "Okay.",
        "Al, are you standing still?"
      ],
      "speaker": "Conrad",
      "time": "132:05:49"
    },
    {
      "tokens": [
        "Yeah, I'll stand still; go ahead."
      ],
      "speaker": "Bean",
      "time": "132:05:53"
    },
    {
      "tokens": [
        "Okay.",
        "I'm standing still.",
        "Houston, on my mark, gonna roll it."
      ],
      "speaker": "Conrad",
      "time": "132:05:54"
    },
    {
      "tokens": [
        "Mark.",
        "It's starting down.",
        "Hit, hit, hit, hit.",
        "(About one second intervals) Now it's just rolling.",
        "Roll, roll, roll, still rolling."
      ],
      "speaker": "Conrad",
      "time": "132:06:00"
    },
    {
      "tokens": [
        "Roger, Pete.",
        "We've got some jiggles..."
      ],
      "speaker": "Schmitt",
      "time": "132:06:13"
    },
    {
      "tokens": [
        "Roll, roll, roll."
      ],
      "speaker": "Conrad",
      "time": "132:06:14"
    },
    {
      "tokens": [
        "...that I can see here.",
        "We'll get a reading on it for you."
      ],
      "speaker": "Schmitt",
      "time": "132:06:15"
    },
    {
      "tokens": [
        "Still rolling.",
        "Still rolling.",
        "Very slowly, still rolling.",
        "And it's stopped..."
      ],
      "speaker": "Conrad",
      "time": "132:06:22"
    },
    {
      "tokens": [
        "Mark.",
        "Stop.",
        "(Pause)"
      ],
      "speaker": "Conrad",
      "time": "132:06:31"
    },
    {
      "tokens": [
        "Okay, Houston, I'm looking at the contrast chart in the shadow and, as I mentioned, at 3 feet I can see all six.",
        "If I back up maybe to 10 feet, as long as I stand here a moment and adapt my eyes, I can see all six, also.",
        "Now, the thing that seems to have the biggest effect on it is how low the Sun is.",
        "The Sun is high now and so I don't have to squint my eyes particularly looking in that direction (of the Sun).",
        "Yesterday, looking into the same crater - even though it wouldn't be any darker in there - because the Sun was there, I would never be able to adapt.",
        "Right now, I can see all six marks, and I've taken the photographs.",
        "Going to go out and do solar wind now."
      ],
      "speaker": "Bean",
      "time": "132:06:37"
    },
    {
      "tokens": [
        "Roger, Al."
      ],
      "speaker": "Schmitt",
      "time": "132:07:23"
    },
    {
      "tokens": [
        "I can't see a lot of difference in visibility here as on Earth, really.",
        "You adapt just as well.",
        "The only major difference I've noticed is the fact that when you're out here on this area, if you look cross-Sun, the Moon appears one color; if you look down-Sun, it's another; if you look up-Sun, it's another.",
        "But looking into shadows or anything else like that, it's pretty much the same as (looking into shadow) on Earth."
      ],
      "speaker": "Bean",
      "time": "132:07:24"
    },
    {
      "tokens": [
        "Copy that, Al."
      ],
      "speaker": "Schmitt",
      "time": "132:07:55"
    },
    {
      "tokens": [
        "Okay, I'll take some pictures here of the solar wind for you.",
        "(Long Pause) It doesn't look as pronounced wrapped around the pole now that I get out here, Houston.",
        "It looks pretty much like yesterday.",
        "I guess it was sort of an optical illusion from inside the spacecraft.",
        "(Pause) I took a couple of pictures of it, but I don't think there's anything unusual going on there."
      ],
      "speaker": "Bean",
      "time": "132:07:59"
    },
    {
      "tokens": [
        "Roger, Al.",
        "And, Pete, if it's convenient and you can find another rock there and give her a heave, Experiments sure would like to see another one."
      ],
      "speaker": "Schmitt",
      "time": "132:08:37"
    },
    {
      "tokens": [
        "Okay, I was setting up my rock hole and all that good things for the polarizing light.",
        "(Pause)"
      ],
      "speaker": "Conrad",
      "time": "132:08:50"
    },
    {
      "tokens": [
        "Say, I was looking at a rock that has small crystals in it.",
        "One of them is shining very, very bright green, like ginger-ale-bottle green.",
        "(Pause)"
      ],
      "speaker": "Conrad",
      "time": "132:09:10"
    },
    {
      "tokens": [
        "Al, are you on your way?"
      ],
      "speaker": "Conrad",
      "time": "132:09:18"
    },
    {
      "tokens": [
        "That's affirm; I'm now making sure that everything is in the Hand Tool Carrier here."
      ],
      "speaker": "Bean",
      "time": "132:09:30"
    },
    {
      "tokens": [
        "Okay."
      ],
      "speaker": "Conrad",
      "time": "132:09:38"
    },
    {
      "tokens": [
        "I'm mounting them pretty firmly.",
        "Hey, Houston.",
        "As I was working around the Hand Tool Carrier a moment ago, the canvas bag (the big sample bag in the middle of the HTC) came loose.",
        "It took me about 2 minutes to put it back together again; it came off the metal sides.",
        "And it looks like those clips that hold it on are going to be completely inadequate and I expect that we're going to have some trouble with it all day today.",
        "Maybe you ought to think about fixing it before the next time (that is, before Apollo 13)."
      ],
      "speaker": "Bean",
      "time": "132:09:39"
    },
    {
      "tokens": [
        "Roger, Al.",
        "We copy that.",
        "Do you think that once you put a little weight in it, she'll hold better?"
      ],
      "speaker": "Gibson",
      "time": "132:10:05"
    },
    {
      "tokens": [
        "I don't know; they don't seem to have a lot of friction on the sides there, and that bag just floats around.",
        "It needs to be more firmly attached some way."
      ],
      "speaker": "Bean",
      "time": "132:10:12"
    },
    {
      "tokens": [
        "Roger."
      ],
      "speaker": "Gibson",
      "time": "132:10:24"
    },
    {
      "tokens": [
        "Okay.",
        "(Pause)"
      ],
      "speaker": "Bean",
      "time": "132:10:25"
    },
    {
      "tokens": [
        "Al?"
      ],
      "speaker": "Conrad",
      "time": "132:10:35"
    },
    {
      "tokens": [
        "Yes, sir."
      ],
      "speaker": "Bean",
      "time": "132:10:36"
    },
    {
      "tokens": [
        "Where are you?"
      ],
      "speaker": "Conrad",
      "time": "132:10:37"
    },
    {
      "tokens": [
        "I'm just leaving the LM."
      ],
      "speaker": "Bean",
      "time": "132:10:38"
    },
    {
      "tokens": [
        "Okay."
      ],
      "speaker": "Conrad",
      "time": "132:10:40"
    }
  ],
  "source_file": "surface_12_rocking_and_rolling_at_head_crater.html"
}